setup.py
lera/__init__.py
lera/keras.py
lera.egg-info/PKG-INFO
lera.egg-info/SOURCES.txt
lera.egg-info/dependency_links.txt
lera.egg-info/entry_points.txt
lera.egg-info/not-zip-safe
lera.egg-info/requires.txt
lera.egg-info/top_level.txt
test/test.py