Metadata-Version: 1.0
Name: lera
Version: 0.2.2
Summary: A journal for your ML experiments. It has lightweight visualization and can store images, sounds, files, models, source code
Home-page: https://lera.ai
Author: Ilya Ovdin
Author-email: iovdin@lera.ai
License: Apache License 2.0
Platform: UNKNOWN
